xmagic_sdk/__about__.py
xmagic_sdk/__init__.py
xmagic_sdk/config.py
xmagic_sdk/agents/__init__.py
xmagic_sdk/agents/agents.py
xmagic_sdk/chatting/__init__.py
xmagic_sdk/chatting/chatting.py
xmagic_sdk/cli/__init__.py
xmagic_sdk/cli/chat.py
xmagic_sdk/cli/configure.py
xmagic_sdk/cli/mcp.py
xmagic_sdk/logging/__init__.py
xmagic_sdk/logging/logging.py
xmagic_sdk/mcp/__init__.py
xmagic_sdk/mcp/artifacts.py
xmagic_sdk/mcp/deploy_mcp.py
xmagic_sdk/mcp/download_files.py
xmagic_sdk/mcp/fetch_info_from_kb.py
xmagic_sdk/mcp/mcp_api.py
xmagic_sdk/mcp/mcp_models.py
xmagic_sdk/mcp/registry.py
xmagic_sdk/models/__init__.py
xmagic_sdk/models/chatting.py
xmagic_sdk/utils/__init__.py
xmagic_sdk/utils/config_utils.py
xmagic_sdk/utils/validations.py
xmagic_sdk-0.0.3.dist-info/METADATA
xmagic_sdk-0.0.3.dist-info/WHEEL
xmagic_sdk-0.0.3.dist-info/entry_points.txt
xmagic_sdk-0.0.3.dist-info/top_level.txt
xmagic_sdk-0.0.3.dist-info/RECORD
