Metadata-Version: 2.4
Name: xmagic-sdk
Version: 0.0.3
Home-page: 
Author: Marcos Rivera Martínez, Glenn Ko, Subhash G N, Jatin Sarda
Author-email: marcos.rm@stochastic.ai, glenn@stochastic.ai, subhash.gn@stochastic.ai
Classifier: Programming Language :: Python :: 3
Classifier: Operating System :: OS Independent
Requires-Python: >=3.9
Requires-Dist: setuptools
Requires-Dist: pydantic
Requires-Dist: numpy
Requires-Dist: requests
Requires-Dist: python-dotenv
Requires-Dist: click
Requires-Dist: bson
Requires-Dist: fastapi
Requires-Dist: uvicorn
Requires-Dist: httpx
Dynamic: author
Dynamic: author-email
Dynamic: classifier
Dynamic: description-content-type
Dynamic: requires-dist
Dynamic: requires-python
